ivy_toml.py
ivy_toml-0.1.0.dist-info/METADATA
ivy_toml-0.1.0.dist-info/WHEEL
ivy_toml-0.1.0.dist-info/top_level.txt
ivy_toml-0.1.0.dist-info/RECORD
