Metadata-Version: 2.1
Name: ivy-toml
Version: 0.1.0
Summary: Adds TOML support to Ivy.
Home-page: https://github.com/dmulholl/ivy_toml
Author: Darren Mulholland
Author-email: UNKNOWN
License: Public Domain
Platform: UNKNOWN
Classifier: Programming Language :: Python :: 3
Classifier: Operating System :: OS Independent
Classifier: License :: Public Domain
Requires-Dist: toml (~=0.10)
